Workbook
Name Administrative: '[1]Cass Lake'!$K$13
Name Marketing: '[1]Cass Lake'!$K$14
Name Operations: '[1]Cass Lake'!$K$15
Name Salaries_Wages: '[1]Cass Lake'!$K$12

Sheet Instructions
A2: Excel Practice Exam 1

Sheet Project 1
A1: Blue Lake Sports
A2: First Quarter Sales by City
A3: Department | B3: Week 1 | C3: Week 2 | D3: Week 3 | E3: Week 4 | F3: Total
A4: Apparel | B4: 2600 | C4: 3200 | D4: 3800 | E4: 3700 | F4: =SUM(January_Sale[[#This Row],[Week 1]:[Week 4]]) -> 13300
A5: Baseball | B5: 3500 | C5: 1200 | D5: 1350 | E5: 2100 | F5: =SUM(January_Sale[[#This Row],[Week 1]:[Week 4]]) -> 8150
A6: Basketball | B6: 1800 | C6: 1800 | D6: 2250 | E6: 1400 | F6: =SUM(January_Sale[[#This Row],[Week 1]:[Week 4]]) -> 7250
A7: Bike & Skate | B7: 1500 | C7: 1325 | D7: 1225 | E7: 2450 | F7: =SUM(January_Sale[[#This Row],[Week 1]:[Week 4]]) -> 6500
A8: Fishing | B8: 2350 | C8: 1035 | D8: 1250 | E8: 2750 | F8: =SUM(January_Sale[[#This Row],[Week 1]:[Week 4]]) -> 7385
A9: Fitness | B9: 2650 | C9: 2875 | D9: 3250 | E9: 3775 | F9: =SUM(January_Sale[[#This Row],[Week 1]:[Week 4]]) -> 12550
A10: Footwear | B10: 1875 | C10: 2675 | D10: 3575 | E10: 3250 | F10: =SUM(January_Sale[[#This Row],[Week 1]:[Week 4]]) -> 11375
A11: Game Room | B11: 1300 | C11: 1500 | D11: 1900 | E11: 1050 | F11: =SUM(January_Sale[[#This Row],[Week 1]:[Week 4]]) -> 5750
A12: Golf | B12: 4750 | C12: 875 | D12: 925 | E12: 5400 | F12: =SUM(January_Sale[[#This Row],[Week 1]:[Week 4]]) -> 11950
A13: Hockey | B13: 850 | C13: 1875 | D13: 1950 | E13: 750 | F13: =SUM(January_Sale[[#This Row],[Week 1]:[Week 4]]) -> 5425
A14: Hunting | B14: 2000 | C14: 1000 | D14: 650 | E14: 725 | F14: =SUM(January_Sale[[#This Row],[Week 1]:[Week 4]]) -> 4375
A15: Lacrosse | B15: 1750 | C15: 1800 | D15: 1750 | E15: 1375 | F15: =SUM(January_Sale[[#This Row],[Week 1]:[Week 4]]) -> 6675
... A17: Winter Sports | B17: 1250 | C17: 34350 | D17: 2750 | E17: 550 | F17: =SUM(January_Sale[[#This Row],[Week 1]:[Week 4]]) -> 38900
A18: Total | B18: =SUBTOTAL(101,January_Sale[Week 1]) -> 2150 | C18: =SUBTOTAL(105,January_Sale[Week 2]) -> 875 | D18: =SUBTOTAL(104,January_Sale[Week 3]) -> 3800 | E18: =MEDIAN(E4:E17) -> 2275 | F18: =SUBTOTAL(109,January_Sale[Total]) -> 149360

Sheet Project 2
A1: San Diego Sailing
A2: Rental and Charter Fleet
A4: Boat ID | B4: Boat Type | C4: Length | D4: Model Year | E4: Seats | F4: Sleeps | G4: Galley with Stove | H4: Half-Day Rate | I4: Full Day Rate
A5: 1010 | B5: Catalina 270 | C5: 28'4" | D5: 2000 | E5: 8 | F5: 6 | G5: =IF(E5>8, "YES", "NO") -> NO | H5: 375 | I5: 650
A6: 1015 | B6: Catalina 270 | C6: 28'4" | D6: 2001 | E6: 8 | F6: 6 | G6: =IF(E6>8, "YES", "NO") -> NO | H6: 425 | I6: 725
A7: 1146 | B7: Hunter 33 | C7: 33'6" | D7: 2004 | E7: 10 | F7: 6 | G7: =IF(E7>8, "YES", "NO") -> YES | H7: 350 | I7: 500
A8: 1150 | B8: Capri 22 Mk II | C8: 24'8" | D8: 2005 | E8: 6 | F8: 4 | G8: =IF(E8>8, "YES", "NO") -> NO | H8: 325 | I8: 500
A9: 1152 | B9: Capri 22 Mk II | C9: 24'8" | D9: 2005 | E9: 6 | F9: 4 | G9: =IF(E9>8, "YES", "NO") -> NO | H9: 325 | I9: 500
A10: 1164 | B10: Capri 22 Mk II | C10: 24'8" | D10: 2006 | E10: 6 | F10: 4 | G10: =IF(E10>8, "YES", "NO") -> NO | H10: 325 | I10: 500
A11: 1168 | B11: Hunter 33 | C11: 33'6" | D11: 2007 | E11: 10 | F11: 6 | G11: =IF(E11>8, "YES", "NO") -> YES | H11: 425 | I11: 725
A12: 1175 | B12: Beneteau 40 | C12: 39'10" | D12: 2008 | E12: 12 | F12: 6 | G12: =IF(E12>8, "YES", "NO") -> YES | H12: 489 | I12: 750
A13: 1180 | B13: Beneteau 373 | C13: 36'11" | D13: 2009 | E13: 10 | F13: 6 | G13: =IF(E13>8, "YES", "NO") -> YES | H13: 369 | I13: 725
A14: 1185 | B14: Hunter 36 | C14: 35'6" | D14: 2009 | E14: 10 | F14: 6 | G14: =IF(E14>8, "YES", "NO") -> YES | H14: 349 | I14: 550
A15: 1190 | B15: Beneteau 373 | C15: 36'11" | D15: 2010 | E15: 10 | F15: 6 | G15: =IF(E15>8, "YES", "NO") -> YES | H15: 369 | I15: 625
A16: 1200 | B16: Beneteau 373 | C16: 36'11" | D16: 2010 | E16: 10 | F16: 6 | G16: =IF(E16>8, "YES", "NO") -> YES | H16: 369 | I16: 625
... A19: 1230 | B19: Catalina 270 | C19: 28'4" | D19: 2012 | E19: 8 | F19: 6 | G19: =IF(E19>8, "YES", "NO") -> NO | H19: 439 | I19: 675

Sheet Project 3
A1: San Diego Sailing
A2: New Prices at 5% and 10% Increases
D3: Half-Day | F3: Full Day
A4: Boat ID | B4: Boat Type | C4: Length | D4: 0.05 | E4: 0.1 | F4: 0.05 | G4: 0.1
A5: 1010 | B5: Catalina 270 | C5: 28'4" | D5: =$D$4*'Project 2'!H5 -> 18.75 | E5: =$E$4*'Project 2'!H5 -> 37.5 | F5: =$F$4*'Project 2'!I5 -> 32.5 | G5: =$G$4*'Project 2'!I5 -> 65
A6: 1015 | B6: Catalina 270 | C6: 28'4" | D6: =$D$4*'Project 2'!H6 -> 21.25 | E6: =$E$4*'Project 2'!H6 -> 42.5 | F6: =$F$4*'Project 2'!I6 -> 36.25 | G6: =$G$4*'Project 2'!I6 -> 72.5
A7: 1146 | B7: Hunter 33 | C7: 33'6" | D7: =$D$4*'Project 2'!H7 -> 17.5 | E7: =$E$4*'Project 2'!H7 -> 35 | F7: =$F$4*'Project 2'!I7 -> 25 | G7: =$G$4*'Project 2'!I7 -> 50
A8: 1150 | B8: Capri 22 Mk II | C8: 24'8" | D8: =$D$4*'Project 2'!H8 -> 16.25 | E8: =$E$4*'Project 2'!H8 -> 32.5 | F8: =$F$4*'Project 2'!I8 -> 25 | G8: =$G$4*'Project 2'!I8 -> 50
A9: 1152 | B9: Capri 22 Mk II | C9: 24'8" | D9: =$D$4*'Project 2'!H9 -> 16.25 | E9: =$E$4*'Project 2'!H9 -> 32.5 | F9: =$F$4*'Project 2'!I9 -> 25 | G9: =$G$4*'Project 2'!I9 -> 50
A10: 1164 | B10: Capri 22 Mk II | C10: 24'8" | D10: =$D$4*'Project 2'!H10 -> 16.25 | E10: =$E$4*'Project 2'!H10 -> 32.5 | F10: =$F$4*'Project 2'!I10 -> 25 | G10: =$G$4*'Project 2'!I10 -> 50
A11: 1168 | B11: Hunter 33 | C11: 33'6" | D11: =$D$4*'Project 2'!H11 -> 21.25 | E11: =$E$4*'Project 2'!H11 -> 42.5 | F11: =$F$4*'Project 2'!I11 -> 36.25 | G11: =$G$4*'Project 2'!I11 -> 72.5
A12: 1175 | B12: Beneteau 40 | C12: 39'10" | D12: =$D$4*'Project 2'!H12 -> 24.45 | E12: =$E$4*'Project 2'!H12 -> 48.9 | F12: =$F$4*'Project 2'!I12 -> 37.5 | G12: =$G$4*'Project 2'!I12 -> 75
A13: 1180 | B13: Beneteau 373 | C13: 36'11" | D13: =$D$4*'Project 2'!H13 -> 18.45 | E13: =$E$4*'Project 2'!H13 -> 36.9 | F13: =$F$4*'Project 2'!I13 -> 36.25 | G13: =$G$4*'Project 2'!I13 -> 72.5
A14: 1185 | B14: Hunter 36 | C14: 35'6" | D14: =$D$4*'Project 2'!H14 -> 17.45 | E14: =$E$4*'Project 2'!H14 -> 34.9 | F14: =$F$4*'Project 2'!I14 -> 27.5 | G14: =$G$4*'Project 2'!I14 -> 55
A15: 1190 | B15: Beneteau 373 | C15: 36'11" | D15: =$D$4*'Project 2'!H15 -> 18.45 | E15: =$E$4*'Project 2'!H15 -> 36.9 | F15: =$F$4*'Project 2'!I15 -> 31.25 | G15: =$G$4*'Project 2'!I15 -> 62.5
A16: 1200 | B16: Beneteau 373 | C16: 36'11" | D16: =$D$4*'Project 2'!H16 -> 18.45 | E16: =$E$4*'Project 2'!H16 -> 36.9 | F16: =$F$4*'Project 2'!I16 -> 31.25 | G16: =$G$4*'Project 2'!I16 -> 62.5
... A19: 1230 | B19: Catalina 270 | C19: 28'4" | D19: =$D$4*'Project 2'!H19 -> 21.95 | E19: =$E$4*'Project 2'!H19 -> 43.9 | F19: =$F$4*'Project 2'!I19 -> 33.75 | G19: =$G$4*'Project 2'!I19 -> 67.5

Sheet Project 4
A1: San Diego Sailing Bookings
A2: Revenue per Passenger
A4: Date | B4: Boat ID | C4: Boat Type | D4: # of Passengers | E4: Total Fees | F4: Fees per Passenger
A5: 42465 | B5: 1010 | C5: Catalina 270 | D5: 4 | E5: 525 | F5: =E5/D5 -> 131.25
A6: 42468 | B6: 1015 | C6: Catalina 270 | D6: 6 | E6: 850 | F6: =E6/D6 -> 141.66667
A7: 42471 | B7: 1146 | C7: Hunter 33 | D7: 6 | E7: 500 | F7: =E7/D7 -> 83.333333
A8: 42474 | B8: 1150 | C8: Capri 22 Mk II | D8: 6 | E8: 525 | F8: =E8/D8 -> 87.5
A9: 42477 | B9: 1152 | C9: Capri 22 Mk II | D9: 4 | E9: 325 | F9: =E9/D9 -> 81.25
A10: 42480 | B10: 1164 | C10: Capri 22 Mk II | D10: 3 | E10: 475 | F10: =E10/D10 -> 158.33333
A11: 42483 | B11: 1168 | C11: Hunter 33 | D11: 6 | E11: 725 | F11: =E11/D11 -> 120.83333
A12: 42486 | B12: 1175 | C12: Beneteau 40 | D12: 10 | E12: 850 | F12: =E12/D12 -> 85
A13: 42489 | B13: 1180 | C13: Beneteau 373 | D13: 8 | E13: 350 | F13: =E13/D13 -> 43.75
A14: 42492 | B14: 1185 | C14: Hunter 36 | D14: 8 | E14: 650 | F14: =E14/D14 -> 81.25
A15: 42495 | B15: 1190 | C15: Beneteau 373 | D15: 10 | E15: 625 | F15: =E15/D15 -> 62.5
A16: 42498 | B16: 1200 | C16: Beneteau 373 | D16: 8 | E16: 725 | F16: =E16/D16 -> 90.625
... A19: 42507 | B19: 1230 | C19: Catalina 270 | D19: 6 | E19: 675 | F19: =E19/D19 -> 112.5
C25: Bookings by Type
D26: Count | E26: Total Fees
C27: Beneteau | D27: =COUNTIF(C5:C19, "*BEN*") -> 5 | E27: =SUMIF(C5:C19, "*ben*", E5:E19) -> 3400
C28: Capri 22 Mk II | D28: =COUNTIF(C5:C19, "*cap*") -> 3 | E28: =SUMIF(C5:C19, "*cap*", E5:E19) -> 1325
C29: Catalina 270 | D29: =COUNTIF(C5:C19,"*cat*") -> 3 | E29: =SUMIF(C5:C19, "*cat*", E5:E19) -> 2050
C30: Hunter | D30: =COUNTIF(C5:C19,"*Hun*") -> 4 | E30: =SUMIF(C5:C19, "*hun*", E5:E19) -> 2600

Sheet Project 5
A1: Classic Gardens and Landscapes (CGL)
A2: Revenue for Quarters 3 and 4
A4: Revenue Categories | B4: July | C4: August | D4: September | E4: October | F4: November | G4: December | H4: Total
A5: Lawn Maintenance | B5: 7660.125 | C5: 7741.125 | D5: 8123.8 | E5: 4500 | F5: 3250 | G5: 1225.75 | H5: =SUM(B5:G5) -> 32500.8
A6: Trees & Plants | B6: 11819.925 | C6: 10456.34 | D6: 12043.125 | E6: 11803.275 | F6: 11879.775 | G6: 12226.275 | H6: =SUM(B6:G6) -> 70228.715
A7: Patio and Furniture | B7: 15192.225 | C7: 13070.475 | D7: 12957.3 | E7: 13039.875 | F7: 15318.225 | G7: 16876.125 | H7: =SUM(B7:G7) -> 86454.225
A8: Fountains and Irrigation | B8: 4478.175 | C8: 4708.125 | D8: 4475.25 | E8: 5153.625 | F8: 5514.525 | G8: 7919.55 | H8: =SUM(B8:G8) -> 32249.25
A9: Landscape Design | B9: 1025 | C9: 1575.35 | D9: 1750 | E9: 1125.45 | F9: 725 | G9: 935.25 | H9: =SUM(B9:G9) -> 7136.05
A10: Total Revenue | B10: =SUM(B5:B9) -> 40175.45 | C10: =SUM(C5:C9) -> 37551.415 | D10: =SUM(D5:D9) -> 39349.475 | E10: =SUM(E5:E9) -> 35622.225 | F10: =SUM(F5:F9) -> 36687.525 | G10: =SUM(G5:G9) -> 39182.95 | H10: =SUM(H5:H9) -> 228569.04

Sheet Project 6
A1: Last Name | B1: First Name | C1: Employee Name | D1: Building | E1: Department | F1: Hire Date | G1: Years | H1: Benefits | I1: Salary | J1: Job Rating
A2: Page | B2: Lisa | C2: =_xlfn.TEXTJOIN(",",TRUE, Employee[[#This Row],[Last Name]], Employee[[#This Row],[First Name]]) -> Page, Lisa | D2: West | E2: ADC | F2: 37249 | G2: 15 | H2: DMR | I2: 60981 | J2: 1
A3: Taylor | B3: Hector | C3: =_xlfn.TEXTJOIN(",",TRUE, Employee[[#This Row],[Last Name]], Employee[[#This Row],[First Name]]) -> Taylor, Hector | D3: West | E3: ADC | F3: 41673 | G3: 3 | H3: DM | I3: 60915 | J3: 4
A4: Dawson | B4: Jonathan | C4: =_xlfn.TEXTJOIN(",",TRUE, Employee[[#This Row],[Last Name]], Employee[[#This Row],[First Name]]) -> Dawson, Jonathan | D4: West | E4: ADC | F4: 40225 | G4: 7 | I4: 97071 | J4: 5
A5: Duran | B5: Brian | C5: =_xlfn.TEXTJOIN(",",TRUE, Employee[[#This Row],[Last Name]], Employee[[#This Row],[First Name]]) -> Duran, Brian | D5: Taft | E5: ADC | F5: 42229 | G5: 2 | I5: 115421 | J5: 3
A6: Weber | B6: Larry | C6: =_xlfn.TEXTJOIN(",",TRUE, Employee[[#This Row],[Last Name]], Employee[[#This Row],[First Name]]) -> Weber, Larry | D6: Watson | E6: ADC | F6: 40525 | G6: 6 | H6: M | I6: 115547 | J6: 4
A7: Pratt | B7: Erik | C7: =_xlfn.TEXTJOIN(",",TRUE, Employee[[#This Row],[Last Name]], Employee[[#This Row],[First Name]]) -> Pratt, Erik | D7: North | E7: Training | F7: 39829 | G7: 8 | H7: DMR | I7: 69212 | J7: 2
A8: O'Connor | B8: Kent | C8: =_xlfn.TEXTJOIN(",",TRUE, Employee[[#This Row],[Last Name]], Employee[[#This Row],[First Name]]) -> O'Connor, Kent | D8: Taft | E8: Training | F8: 37295 | G8: 15 | H8: DMR | I8: 120198 | J8: 1
A9: Spencer | B9: Boyd | C9: =_xlfn.TEXTJOIN(",",TRUE, Employee[[#This Row],[Last Name]], Employee[[#This Row],[First Name]]) -> Spencer, Boyd | D9: Main | E9: Training | F9: 40267 | G9: 7 | I9: 107635 | J9: 5
A10: Wiggins | B10: Frank | C10: =_xlfn.TEXTJOIN(",",TRUE, Employee[[#This Row],[Last Name]], Employee[[#This Row],[First Name]]) -> Wiggins, Frank | D10: North | E10: Training | F10: 37338 | G10: 15 | H10: DMR | I10: 113020 | J10: 1
A11: Tanner | B11: Timothy | C11: =_xlfn.TEXTJOIN(",",TRUE, Employee[[#This Row],[Last Name]], Employee[[#This Row],[First Name]]) -> Tanner, Timothy | D11: Taft | E11: Training | F11: 38482 | G11: 12 | H11: DMR | I11: 82341 | J11: 4
A12: Strickland | B12: Rajean | C12: =_xlfn.TEXTJOIN(",",TRUE, Employee[[#This Row],[Last Name]], Employee[[#This Row],[First Name]]) -> Strickland, Rajean | D12: Main | E12: Training | F12: 38860 | G12: 11 | H12: D | I12: 98598 | J12: 3
A13: Chase | B13: Troy | C13: =_xlfn.TEXTJOIN(",",TRUE, Employee[[#This Row],[Last Name]], Employee[[#This Row],[First Name]]) -> Chase, Troy | D13: Main | E13: Training | F13: 39220 | G13: 10 | H13: DMR | I13: 46350 | J13: 4
A14: Brewer | B14: Kent | C14: =_xlfn.TEXTJOIN(",",TRUE, Employee[[#This Row],[Last Name]], Employee[[#This Row],[First Name]]) -> Brewer, Kent | D14: Main | E14: Training | F14: 41857 | G14: 3 | H14: DM | I14: 61076 | J14: 1
A15: Wilkins | B15: Jesse | C15: =_xlfn.TEXTJOIN(",",TRUE, Employee[[#This Row],[Last Name]], Employee[[#This Row],[First Name]]) -> Wilkins, Jesse | D15: North | E15: Training | F15: 42214 | G15: 2 | H15: DMR | I15: 107968 | J15: 5
A16: White | B16: Daniel | C16: =_xlfn.TEXTJOIN(",",TRUE, Employee[[#This Row],[Last Name]], Employee[[#This Row],[First Name]]) -> White, Daniel | D16: Watson | E16: Training | F16: 37842 | G16: 14 | H16: D | I16: 102146 | J16: 4
A17: Holland | B17: Donald | C17: =_xlfn.TEXTJOIN(",",TRUE, Employee[[#This Row],[Last Name]], Employee[[#This Row],[First Name]]) -> Holland, Donald | D17: South | E17: Training | F17: 41865 | G17: 3 | H17: DMR | I17: 46009 | J17: 3
A18: Rowe | B18: Ken | C18: =_xlfn.TEXTJOIN(",",TRUE, Employee[[#This Row],[Last Name]], Employee[[#This Row],[First Name]]) -> Rowe, Ken | D18: West | E18: Training | F18: 37855 | G18: 14 | I18: 53399 | J18: 3
A19: Burton | B19: Cam | C19: =_xlfn.TEXTJOIN(",",TRUE, Employee[[#This Row],[Last Name]], Employee[[#This Row],[First Name]]) -> Burton, Cam | D19: West | E19: Training | F19: 40782 | G19: 6 | H19: D | I19: 45419 | J19: 5
A20: Phillips | B20: Liesl | C20: =_xlfn.TEXTJOIN(",",TRUE, Employee[[#This Row],[Last Name]], Employee[[#This Row],[First Name]]) -> Phillips, Liesl | D20: South | E20: Training | F20: 40107 | G20: 7 | H20: R | I20: 69038 | J20: 2
A21: Gallagher | B21: Johnson | C21: =_xlfn.TEXTJOIN(",",TRUE, Employee[[#This Row],[Last Name]], Employee[[#This Row],[First Name]]) -> Gallagher, Johnson | D21: West | E21: Training | F21: 41204 | G21: 4 | I21: 46163 | J21: 4
A22: Wolf | B22: Debbie | C22: =_xlfn.TEXTJOIN(",",TRUE, Employee[[#This Row],[Last Name]], Employee[[#This Row],[First Name]]) -> Wolf, Debbie | D22: Taft | E22: Training | F22: 37221 | G22: 15 | H22: R | I22: 70990 | J22: 5
A23: Todd | B23: Steven | C23: =_xlfn.TEXTJOIN(",",TRUE, Employee[[#This Row],[Last Name]], Employee[[#This Row],[First Name]]) -> Todd, Steven | D23: Watson | E23: Training | F23: 40147 | G23: 7 | H23: M | I23: 45315 | J23: 3
A24: McKenzie | B24: Michelle | C24: =_xlfn.TEXTJOIN(",",TRUE, Employee[[#This Row],[Last Name]], Employee[[#This Row],[First Name]]) -> McKenzie, Michelle | D24: Main | E24: Environmental Compliance | F24: 39824 | G24: 8 | H24: R | I24: 102687 | J24: 2
A25: Thornton | B25: Charles | C25: =_xlfn.TEXTJOIN(",",TRUE, Employee[[#This Row],[Last Name]], Employee[[#This Row],[First Name]]) -> Thornton, Charles | D25: West | E25: Environmental Compliance | F25: 37971 | G25: 13 | H25: R | I25: 121213 | J25: 3
A26: Dunn | B26: Matthew | C26: =_xlfn.TEXTJOIN(",",TRUE, Employee[[#This Row],[Last Name]], Employee[[#This Row],[First Name]]) -> Dunn, Matthew | D26: North | E26: Environmental Compliance | F26: 37292 | G26: 15 | H26: D | I26: 74666 | J26: 1
A27: Potter | B27: Dawn | C27: =_xlfn.TEXTJOIN(",",TRUE, Employee[[#This Row],[Last Name]], Employee[[#This Row],[First Name]]) -> Potter, Dawn | D27: Taft | E27: Environmental Compliance | F27: 39129 | G27: 10 | H27: DMR | I27: 90032 | J27: 1
A28: Carroll | B28: Lesa | C28: =_xlfn.TEXTJOIN(",",TRUE, Employee[[#This Row],[Last Name]], Employee[[#This Row],[First Name]]) -> Carroll, Lesa | D28: West | E28: Environmental Compliance | F28: 37697 | G28: 14 | H28: M | I28: 43469 | J28: 1
A29: Fleming | B29: Irv | C29: =_xlfn.TEXTJOIN(",",TRUE, Employee[[#This Row],[Last Name]], Employee[[#This Row],[First Name]]) -> Fleming, Irv | D29: West | E29: Environmental Compliance | F29: 39929 | G29: 8 | H29: DMR | I29: 68870 | J29: 1
A30: Nguyen | B30: Dennis | C30: =_xlfn.TEXTJOIN(",",TRUE, Employee[[#This Row],[Last Name]], Employee[[#This Row],[First Name]]) -> Nguyen, Dennis | D30: Main | E30: Environmental Compliance | F30: 40039 | G30: 8 | I30: 113141 | J30: 4
A31: Blair | B31: Sperry | C31: =_xlfn.TEXTJOIN(",",TRUE, Employee[[#This Row],[Last Name]], Employee[[#This Row],[First Name]]) -> Blair, Sperry | D31: West | E31: Environmental Compliance | F31: 41184 | G31: 5 | H31: DM | I31: 104719 | J31: 3
A32: Wyatt | B32: Kelly | C32: =_xlfn.TEXTJOIN(",",TRUE, Employee[[#This Row],[Last Name]], Employee[[#This Row],[First Name]]) -> Wyatt, Kelly | D32: West | E32: Environmental Compliance | F32: 41934 | G32: 2 | H32: DM | I32: 61443 | J32: 2
A33: Walton | B33: Benjamin | C33: =_xlfn.TEXTJOIN(",",TRUE, Employee[[#This Row],[Last Name]], Employee[[#This Row],[First Name]]) -> Walton, Benjamin | D33: North | E33: Environmental Compliance | F33: 40492 | G33: 6 | H33: DMR | I33: 115351 | J33: 1
A34: Beck | B34: Craig | C34: =_xlfn.TEXTJOIN(",",TRUE, Employee[[#This Row],[Last Name]], Employee[[#This Row],[First Name]]) -> Beck, Craig | D34: North | E34: Environmental Compliance | F34: 42096 | G34: 2 | H34: DMR | I34: 71321 | J34: 3
A35: Phelps | B35: Gretchen | C35: =_xlfn.TEXTJOIN(",",TRUE, Employee[[#This Row],[Last Name]], Employee[[#This Row],[First Name]]) -> Phelps, Gretchen | D35: South | E35: Environmental Compliance | F35: 41586 | G35: 3 | I35: 124798 | J35: 2
A36: Bond | B36: John | C36: =_xlfn.TEXTJOIN(",",TRUE, Employee[[#This Row],[Last Name]], Employee[[#This Row],[First Name]]) -> Bond, John | D36: North | E36: Environmental Compliance | F36: 40495 | G36: 6 | H36: M | I36: 96545 | J36: 3
A37: Chang | B37: Gabriel | C37: =_xlfn.TEXTJOIN(",",TRUE, Employee[[#This Row],[Last Name]], Employee[[#This Row],[First Name]]) -> Chang, Gabriel | D37: Main | E37: Environmental Compliance | F37: 41230 | G37: 4 | H37: R | I37: 98833 | J37: 1
A38: Bullock | B38: Greg | C38: =_xlfn.TEXTJOIN(",",TRUE, Employee[[#This Row],[Last Name]], Employee[[#This Row],[First Name]]) -> Bullock, Greg | D38: North | E38: Facilities/Engineering | F38: 42003 | G38: 2 | I38: 124698 | J38: 3
A39: Wheeler | B39: Meegan | C39: =_xlfn.TEXTJOIN(",",TRUE, Employee[[#This Row],[Last Name]], Employee[[#This Row],[First Name]]) -> Wheeler, Meegan | D39: West | E39: Facilities/Engineering | F39: 40172 | G39: 7 | I39: 106453 | J39: 4
A40: Cunningham | B40: Denise | C40: =_xlfn.TEXTJOIN(",",TRUE, Employee[[#This Row],[Last Name]], Employee[[#This Row],[First Name]]) -> Cunningham, Denise | D40: Main | E40: Facilities/Engineering | F40: 41278 | G40: 4 | H40: M | I40: 88169 | J40: 5
A41: Simpson | B41: Jimmy | C41: =_xlfn.TEXTJOIN(",",TRUE, Employee[[#This Row],[Last Name]], Employee[[#This Row],[First Name]]) -> Simpson, Jimmy | D41: Watson | E41: Facilities/Engineering | F41: 37974 | G41: 13 | H41: DMR | I41: 83157 | J41: 3
A42: Griffith | B42: Michelle | C42: =_xlfn.TEXTJOIN(",",TRUE, Employee[[#This Row],[Last Name]], Employee[[#This Row],[First Name]]) -> Griffith, Michelle | D42: South | E42: Facilities/Engineering | F42: 41311 | G42: 4 | I42: 71963 | J42: 2
A43: Powers | B43: Tia | C43: =_xlfn.TEXTJOIN(",",TRUE, Employee[[#This Row],[Last Name]], Employee[[#This Row],[First Name]]) -> Powers, Tia | D43: North | E43: Facilities/Engineering | F43: 36907 | G43: 16 | H43: DMR | I43: 84121 | J43: 3
A44: Navarro | B44: Marc | C44: =_xlfn.TEXTJOIN(",",TRUE, Employee[[#This Row],[Last Name]], Employee[[#This Row],[First Name]]) -> Navarro, Marc | D44: Main | E44: Facilities/Engineering | F44: 36920 | G44: 16 | H44: D | I44: 73059 | J44: 4
A45: Briggs | B45: Bryan | C45: =_xlfn.TEXTJOIN(",",TRUE, Employee[[#This Row],[Last Name]], Employee[[#This Row],[First Name]]) -> Briggs, Bryan | D45: Main | E45: Facilities/Engineering | F45: 36926 | G45: 16 | I45: 115255 | J45: 5
A46: Warren | B46: Jean | C46: =_xlfn.TEXTJOIN(",",TRUE, Employee[[#This Row],[Last Name]], Employee[[#This Row],[First Name]]) -> Warren, Jean | D46: Taft | E46: Facilities/Engineering | F46: 41653 | G46: 3 | H46: D | I46: 75259 | J46: 2
A47: McDonald | B47: Debra | C47: =_xlfn.TEXTJOIN(",",TRUE, Employee[[#This Row],[Last Name]], Employee[[#This Row],[First Name]]) -> McDonald, Debra | D47: North | E47: Facilities/Engineering | F47: 41674 | G47: 3 | H47: M | I47: 104597 | J47: 5
A48: Pitts | B48: Dana | C48: =_xlfn.TEXTJOIN(",",TRUE, Employee[[#This Row],[Last Name]], Employee[[#This Row],[First Name]]) -> Pitts, Dana | D48: Taft | E48: Facilities/Engineering | F48: 42061 | G48: 2 | I48: 124141 | J48: 1
A49: Pruitt | B49: Randy | C49: =_xlfn.TEXTJOIN(",",TRUE, Employee[[#This Row],[Last Name]], Employee[[#This Row],[First Name]]) -> Pruitt, Randy | D49: Main | E49: Facilities/Engineering | F49: 39870 | G49: 8 | I49: 119465 | J49: 5
A50: Nicholson | B50: Lee | C50: =_xlfn.TEXTJOIN(",",TRUE, Employee[[#This Row],[Last Name]], Employee[[#This Row],[First Name]]) -> Nicholson, Lee | D50: West | E50: Facilities/Engineering | F50: 39882 | G50: 8 | H50: M | I50: 51489 | J50: 4
A51: Matthews | B51: Diane | C51: =_xlfn.TEXTJOIN(",",TRUE, Employee[[#This Row],[Last Name]], Employee[[#This Row],[First Name]]) -> Matthews, Diane | D51: North | E51: Facilities/Engineering | F51: 37680 | G51: 14 | I51: 46075 | J51: 3
A52: Norris | B52: Tamara | C52: =_xlfn.TEXTJOIN(",",TRUE, Employee[[#This Row],[Last Name]], Employee[[#This Row],[First Name]]) -> Norris, Tamara | D52: West | E52: Facilities/Engineering | F52: 41731 | G52: 3 | H52: D | I52: 102833 | J52: 2
A53: Weiss | B53: Marisa | C53: =_xlfn.TEXTJOIN(",",TRUE, Employee[[#This Row],[Last Name]], Employee[[#This Row],[First Name]]) -> Weiss, Marisa | D53: West | E53: Facilities/Engineering | F53: 41351 | G53: 4 | I53: 65490 | J53: 2
A54: Lawrence | B54: Ronald | C54: =_xlfn.TEXTJOIN(",",TRUE, Employee[[#This Row],[Last Name]], Employee[[#This Row],[First Name]]) -> Lawrence, Ronald | D54: Main | E54: Facilities/Engineering | F54: 36980 | G54: 16 | I54: 109822 | J54: 3
A55: Sherman | B55: Karin | C55: =_xlfn.TEXTJOIN(",",TRUE, Employee[[#This Row],[Last Name]], Employee[[#This Row],[First Name]]) -> Sherman, Karin | D55: North | E55: Facilities/Engineering | F55: 38086 | G55: 13 | H55: DMR | I55: 93149 | J55: 4
A56: Harmon | B56: Paul | C56: =_xlfn.TEXTJOIN(",",TRUE, Employee[[#This Row],[Last Name]], Employee[[#This Row],[First Name]]) -> Harmon, Paul | D56: North | E56: Facilities/Engineering | F56: 38426 | G56: 12 | H56: DM | I56: 79729 | J56: 3
A57: Vance | B57: Cheryl | C57: =_xlfn.TEXTJOIN(",",TRUE, Employee[[#This Row],[Last Name]], Employee[[#This Row],[First Name]]) -> Vance, Cheryl | D57: South | E57: Facilities/Engineering | F57: 41000 | G57: 5 | I57: 54814 | J57: 3
A58: Swanson | B58: Vicki | C58: =_xlfn.TEXTJOIN(",",TRUE, Employee[[#This Row],[Last Name]], Employee[[#This Row],[First Name]]) -> Swanson, Vicki | D58: Main | E58: Facilities/Engineering | F58: 41352 | G58: 4 | H58: DM | I58: 96191 | J58: 1
A59: Steele | B59: Gerald | C59: =_xlfn.TEXTJOIN(",",TRUE, Employee[[#This Row],[Last Name]], Employee[[#This Row],[First Name]]) -> Steele, Gerald | D59: West | E59: Facilities/Engineering | F59: 41370 | G59: 4 | H59: DMR | I59: 112396 | J59: 1
A60: Richardson | B60: Debbie | C60: =_xlfn.TEXTJOIN(",",TRUE, Employee[[#This Row],[Last Name]], Employee[[#This Row],[First Name]]) -> Richardson, Debbie | D60: North | E60: Facilities/Engineering | F60: 42129 | G60: 2 | H60: DM | I60: 118240 | J60: 3
A61: Whitehead | B61: Carolyn | C61: =_xlfn.TEXTJOIN(",",TRUE, Employee[[#This Row],[Last Name]], Employee[[#This Row],[First Name]]) -> Whitehead, Carolyn | D61: North | E61: Facilities/Engineering | F61: 40666 | G61: 6 | H61: DM | I61: 114408 | J61: 5
A62: Flowers | B62: Kathleen | C62: =_xlfn.TEXTJOIN(",",TRUE, Employee[[#This Row],[Last Name]], Employee[[#This Row],[First Name]]) -> Flowers, Kathleen | D62: Main | E62: Facilities/Engineering | F62: 40293 | G62: 7 | H62: DMR | I62: 104133 | J62: 5
A63: Huff | B63: Erik | C63: =_xlfn.TEXTJOIN(",",TRUE, Employee[[#This Row],[Last Name]], Employee[[#This Row],[First Name]]) -> Huff, Erik | D63: Taft | E63: Facilities/Engineering | F63: 41388 | G63: 4 | H63: D | I63: 99457 | J63: 5
A64: Deleon | B64: Jaquelyn | C64: =_xlfn.TEXTJOIN(",",TRUE, Employee[[#This Row],[Last Name]], Employee[[#This Row],[First Name]]) -> Deleon, Jaquelyn | D64: North | E64: Facilities/Engineering | F64: 41398 | G64: 4 | H64: M | I64: 49254 | J64: 3
A65: Kent | B65: Angus | C65: =_xlfn.TEXTJOIN(",",TRUE, Employee[[#This Row],[Last Name]], Employee[[#This Row],[First Name]]) -> Kent, Angus | D65: North | E65: Facilities/Engineering | F65: 39934 | G65: 8 | I65: 126756 | J65: 2
A66: Wallace | B66: Timothy | C66: =_xlfn.TEXTJOIN(",",TRUE, Employee[[#This Row],[Last Name]], Employee[[#This Row],[First Name]]) -> Wallace, Timothy | D66: Watson | E66: Facilities/Engineering | F66: 37018 | G66: 16 | I66: 115133 | J66: 5
A67: Nichols | B67: Nathaniel | C67: =_xlfn.TEXTJOIN(",",TRUE, Employee[[#This Row],[Last Name]], Employee[[#This Row],[First Name]]) -> Nichols, Nathaniel | D67: North | E67: Facilities/Engineering | F67: 38096 | G67: 13 | H67: R | I67: 101108 | J67: 4
A68: Morgan | B68: Patricia | C68: =_xlfn.TEXTJOIN(",",TRUE, Employee[[#This Row],[Last Name]], Employee[[#This Row],[First Name]]) -> Morgan, Patricia | D68: North | E68: Facilities/Engineering | F68: 41037 | G68: 5 | I68: 62211 | J68: 5
A69: Harding | B69: Erin | C69: =_xlfn.TEXTJOIN(",",TRUE, Employee[[#This Row],[Last Name]], Employee[[#This Row],[First Name]]) -> Harding, Erin | D69: West | E69: Facilities/Engineering | F69: 37043 | G69: 16 | H69: M | I69: 70796 | J69: 4
A70: Hood | B70: Renee | C70: =_xlfn.TEXTJOIN(",",TRUE, Employee[[#This Row],[Last Name]], Employee[[#This Row],[First Name]]) -> Hood, Renee | D70: North | E70: Facilities/Engineering | F70: 38863 | G70: 11 | H70: R | I70: 67727 | J70: 4
A71: Hickman | B71: John | C71: =_xlfn.TEXTJOIN(",",TRUE, Employee[[#This Row],[Last Name]], Employee[[#This Row],[First Name]]) -> Hickman, John | D71: West | E71: Facilities/Engineering | F71: 42169 | G71: 2 | H71: DMR | I71: 109199 | J71: 2
A72: Schneider | B72: Gay | C72: =_xlfn.TEXTJOIN(",",TRUE, Employee[[#This Row],[Last Name]], Employee[[#This Row],[First Name]]) -> Schneider, Gay | D72: Main | E72: Facilities/Engineering | F72: 40357 | G72: 7 | H72: DMR | I72: 119300 | J72: 3
A73: Stone | B73: Brian | C73: =_xlfn.TEXTJOIN(",",TRUE, Employee[[#This Row],[Last Name]], Employee[[#This Row],[First Name]]) -> Stone, Brian | D73: North | E73: Facilities/Engineering | F73: 41446 | G73: 4 | I73: 124619 | J73: 5
A74: Goodman | B74: Kuyler | C74: =_xlfn.TEXTJOIN(",",TRUE, Employee[[#This Row],[Last Name]], Employee[[#This Row],[First Name]]) -> Goodman, Kuyler | D74: North | E74: Facilities/Engineering | F74: 41855 | G74: 3 | H74: DM | I74: 62470 | J74: 3
A75: Simmons | B75: Robert | C75: =_xlfn.TEXTJOIN(",",TRUE, Employee[[#This Row],[Last Name]], Employee[[#This Row],[First Name]]) -> Simmons, Robert | D75: North | E75: Facilities/Engineering | F75: 40740 | G75: 6 | H75: D | I75: 53191 | J75: 4
A76: Wolfe | B76: Keith | C76: =_xlfn.TEXTJOIN(",",TRUE, Employee[[#This Row],[Last Name]], Employee[[#This Row],[First Name]]) -> Wolfe, Keith | D76: West | E76: Facilities/Engineering | F76: 40032 | G76: 8 | H76: DMR | I76: 45299 | J76: 4
A77: Conway | B77: Brett | C77: =_xlfn.TEXTJOIN(",",TRUE, Employee[[#This Row],[Last Name]], Employee[[#This Row],[First Name]]) -> Conway, Brett | D77: South | E77: Facilities/Engineering | F77: 37116 | G77: 16 | I77: 118113 | J77: 3
A78: Mendoza | B78: Bobby | C78: =_xlfn.TEXTJOIN(",",TRUE, Employee[[#This Row],[Last Name]], Employee[[#This Row],[First Name]]) -> Mendoza, Bobby | D78: West | E78: Facilities/Engineering | F78: 37137 | G78: 16 | I78: 112624 | J78: 5
A79: James | B79: Lynn | C79: =_xlfn.TEXTJOIN(",",TRUE, Employee[[#This Row],[Last Name]], Employee[[#This Row],[First Name]]) -> James, Lynn | D79: West | E79: Facilities/Engineering | F79: 40048 | G79: 8 | I79: 105125 | J79: 3
A80: Porter | B80: Rachel | C80: =_xlfn.TEXTJOIN(",",TRUE, Employee[[#This Row],[Last Name]], Employee[[#This Row],[First Name]]) -> Porter, Rachel | D80: Main | E80: Facilities/Engineering | F80: 41163 | G80: 5 | H80: DMR | I80: 51385 | J80: 5
A81: Mullins | B81: Angela | C81: =_xlfn.TEXTJOIN(",",TRUE, Employee[[#This Row],[Last Name]], Employee[[#This Row],[First Name]]) -> Mullins, Angela | D81: Main | E81: Facilities/Engineering | F81: 41910 | G81: 3 | H81: R | I81: 82217 | J81: 4
A82: Poole | B82: Tracy | C82: =_xlfn.TEXTJOIN(",",TRUE, Employee[[#This Row],[Last Name]], Employee[[#This Row],[First Name]]) -> Poole, Tracy | D82: North | E82: Facilities/Engineering | F82: 42278 | G82: 2 | H82: R | I82: 95620 | J82: 4
A83: Farrell | B83: Laura | C83: =_xlfn.TEXTJOIN(",",TRUE, Employee[[#This Row],[Last Name]], Employee[[#This Row],[First Name]]) -> Farrell, Laura | D83: Watson | E83: Facilities/Engineering | F83: 40457 | G83: 7 | H83: DMR | I83: 47514 | J83: 5
A84: Perry | B84: Christopher | C84: =_xlfn.TEXTJOIN(",",TRUE, Employee[[#This Row],[Last Name]], Employee[[#This Row],[First Name]]) -> Perry, Christopher | D84: West | E84: Facilities/Engineering | F84: 37165 | G84: 16 | I84: 105647 | J84: 1
A85: Fletcher | B85: Brian | C85: =_xlfn.TEXTJOIN(",",TRUE, Employee[[#This Row],[Last Name]], Employee[[#This Row],[First Name]]) -> Fletcher, Brian | D85: Main | E85: Facilities/Engineering | F85: 38254 | G85: 13 | H85: M | I85: 125512 | J85: 2
A86: York | B86: Steven | C86: =_xlfn.TEXTJOIN(",",TRUE, Employee[[#This Row],[Last Name]], Employee[[#This Row],[First Name]]) -> York, Steven | D86: North | E86: Facilities/Engineering | F86: 40843 | G86: 5 | I86: 45315 | J86: 3
A87: Hudson | B87: Lorna | C87: =_xlfn.TEXTJOIN(",",TRUE, Employee[[#This Row],[Last Name]], Employee[[#This Row],[First Name]]) -> Hudson, Lorna | D87: West | E87: Facilities/Engineering | F87: 37548 | G87: 15 | I87: 52224 | J87: 3
A88: May | B88: Steve | C88: =_xlfn.TEXTJOIN(",",TRUE, Employee[[#This Row],[Last Name]], Employee[[#This Row],[First Name]]) -> May, Steve | D88: West | E88: Facilities/Engineering | F88: 37565 | G88: 14 | I88: 110399 | J88: 5
A89: Booker | B89: Judith | C89: =_xlfn.TEXTJOIN(",",TRUE, Employee[[#This Row],[Last Name]], Employee[[#This Row],[First Name]]) -> Booker, Judith | D89: West | E89: Facilities/Engineering | F89: 40118 | G89: 7 | I89: 88499 | J89: 4
A90: Dorsey | B90: Matthew | C90: =_xlfn.TEXTJOIN(",",TRUE, Employee[[#This Row],[Last Name]], Employee[[#This Row],[First Name]]) -> Dorsey, Matthew | D90: Main | E90: Facilities/Engineering | F90: 41579 | G90: 3 | H90: M | I90: 104499 | J90: 3
A91: Gardner | B91: Anthony | C91: =_xlfn.TEXTJOIN(",",TRUE, Employee[[#This Row],[Last Name]], Employee[[#This Row],[First Name]]) -> Gardner, Anthony | D91: Main | E91: Facilities/Engineering | F91: 40881 | G91: 5 | I91: 108152 | J91: 1
A92: Hammond | B92: Robert | C92: =_xlfn.TEXTJOIN(",",TRUE, Employee[[#This Row],[Last Name]], Employee[[#This Row],[First Name]]) -> Hammond, Robert | D92: Main | E92: Facilities/Engineering | F92: 41958 | G92: 2 | H92: DM | I92: 126555 | J92: 5
A93: Clayton | B93: Gregory | C93: =_xlfn.TEXTJOIN(",",TRUE, Employee[[#This Row],[Last Name]], Employee[[#This Row],[First Name]]) -> Clayton, Gregory | D93: North | E93: Facilities/Engineering | F93: 37584 | G93: 14 | H93: R | I93: 57059 | J93: 1
A94: Martinez | B94: Kathleen | C94: =_xlfn.TEXTJOIN(",",TRUE, Employee[[#This Row],[Last Name]], Employee[[#This Row],[First Name]]) -> Martinez, Kathleen | D94: Main | E94: Facilities/Engineering | F94: 38319 | G94: 12 | H94: DMR | I94: 123803 | J94: 5
A95: Becker | B95: Gretchen | C95: =_xlfn.TEXTJOIN(",",TRUE, Employee[[#This Row],[Last Name]], Employee[[#This Row],[First Name]]) -> Becker, Gretchen | D95: West | E95: Facilities/Engineering | F95: 39038 | G95: 10 | H95: DMR | I95: 85917 | J95: 5
A96: Thompson | B96: John | C96: =_xlfn.TEXTJOIN(",",TRUE, Employee[[#This Row],[Last Name]], Employee[[#This Row],[First Name]]) -> Thompson, John | D96: Watson | E96: Facilities/Engineering | F96: 40880 | G96: 5 | H96: D | I96: 53330 | J96: 3
A97: Cortez | B97: Jack | C97: =_xlfn.TEXTJOIN(",",TRUE, Employee[[#This Row],[Last Name]], Employee[[#This Row],[First Name]]) -> Cortez, Jack | D97: Main | E97: Green Building | F97: 40570 | G97: 6 | H97: DMR | I97: 73102 | J97: 4
A98: Hardin | B98: Gregory | C98: =_xlfn.TEXTJOIN(",",TRUE, Employee[[#This Row],[Last Name]], Employee[[#This Row],[First Name]]) -> Hardin, Gregory | D98: North | E98: Green Building | F98: 39833 | G98: 8 | I98: 112538 | J98: 2
A99: Pacheco | B99: Therese | C99: =_xlfn.TEXTJOIN(",",TRUE, Employee[[#This Row],[Last Name]], Employee[[#This Row],[First Name]]) -> Pacheco, Therese | D99: Main | E99: Green Building | F99: 40607 | G99: 6 | I99: 43819 | J99: 4
A100: Stokes | B100: Jonathan | C100: =_xlfn.TEXTJOIN(",",TRUE, Employee[[#This Row],[Last Name]], Employee[[#This Row],[First Name]]) -> Stokes, Jonathan | D100: North | E100: Green Building | F100: 41331 | G100: 4 | I100: 85139 | J100: 5
...

Sheet Project 7
A1: The Roux Academy of Art
A5: 2017 Faculty Members
A6: Position | B6: Staff Member | C6: Department | D6: Left | E6: Right | F6: Length | G6: Password
A7: Admin Assistant | B7: Nell Gomez | C7: Admin | D7: =LEFT(B7, 3) -> Nel | E7: =RIGHT(A7, 5) -> stant | F7: =LEN(B7) -> 10 | G7: =_xlfn.CONCAT(D7, E7, F7) -> Nelstant10
A8: Asst. Headmaster | B8: Roland Hale | C8: Admin | D8: =LEFT(B8, 3) -> Rol | E8: =RIGHT(A8, 5) -> aster | F8: =LEN(B8) -> 11 | G8: =_xlfn.CONCAT(D8, E8, F8) -> Rolaster11
A9: Counselor | B9: Bob Steele | C9: Admin | D9: =LEFT(B9, 3) -> Bob | E9: =RIGHT(A9, 5) -> selor | F9: =LEN(B9) -> 10 | G9: =_xlfn.CONCAT(D9, E9, F9) -> Bobselor10
A10: Counselor | B10: Lauryn Drake | C10: Admin | D10: =LEFT(B10, 3) -> Lau | E10: =RIGHT(A10, 5) -> selor | F10: =LEN(B10) -> 12 | G10: =_xlfn.CONCAT(D10, E10, F10) -> Lauselor12
A11: Counselor | B11: Trinidad Faulkner | C11: Admin | D11: =LEFT(B11, 3) -> Tri | E11: =RIGHT(A11, 5) -> selor | F11: =LEN(B11) -> 17 | G11: =_xlfn.CONCAT(D11, E11, F11) -> Triselor17
A12: Counselor | B12: Sixta Jarvis | C12: Admin | D12: =LEFT(B12, 3) -> Six | E12: =RIGHT(A12, 5) -> selor | F12: =LEN(B12) -> 12 | G12: =_xlfn.CONCAT(D12, E12, F12) -> Sixselor12
A13: Counselor | B13: Shayna Cantrell | C13: Admin | D13: =LEFT(B13, 3) -> Sha | E13: =RIGHT(A13, 5) -> selor | F13: =LEN(B13) -> 15 | G13: =_xlfn.CONCAT(D13, E13, F13) -> Shaselor15
A14: Headmaster | B14: Deneen Richards | C14: Admin | D14: =LEFT(B14, 3) -> Den | E14: =RIGHT(A14, 5) -> aster | F14: =LEN(B14) -> 15 | G14: =_xlfn.CONCAT(D14, E14, F14) -> Denaster15
A15: Janitorial | B15: Rubye Donaldson | C15: Admin | D15: =LEFT(B15, 3) -> Rub | E15: =RIGHT(A15, 5) -> orial | F15: =LEN(B15) -> 15 | G15: =_xlfn.CONCAT(D15, E15, F15) -> Ruborial15
A16: Janitorial | B16: Fannie Buckner | C16: Admin | D16: =LEFT(B16, 3) -> Fan | E16: =RIGHT(A16, 5) -> orial | F16: =LEN(B16) -> 14 | G16: =_xlfn.CONCAT(D16, E16, F16) -> Fanorial14
A17: Nurse | B17: Luann Hull | C17: Admin | D17: =LEFT(B17, 3) -> Lua | E17: =RIGHT(A17, 5) -> Nurse | F17: =LEN(B17) -> 10 | G17: =_xlfn.CONCAT(D17, E17, F17) -> LuaNurse10
A18: Secretary | B18: Dorie Salinas | C18: Admin | D18: =LEFT(B18, 3) -> Dor | E18: =RIGHT(A18, 5) -> etary | F18: =LEN(B18) -> 13 | G18: =_xlfn.CONCAT(D18, E18, F18) -> Doretary13
... A35: Photography | B35: Bee Anthony | C35: Teacher | D35: =LEFT(B35, 3) -> Bee | E35: =RIGHT(A35, 5) -> raphy | F35: =LEN(B35) -> 11 | G35: =_xlfn.CONCAT(D35, E35, F35) -> Beeraphy11
