Workbook
Name Commission: " "
Name NewPrice: 'Project 6'!$M$18
Name NewPrice: 'Project 5'!$M$19

Sheet Start Instructions
B2: Excel Practice Exam 3
B4: Start Instructions
B5: 50 Minute Time Allotment
B6: 1 | C6: Save this file as "[FirstName] [LastName]-Practice Exam 3".
B7: 2 | C7: Add the following Document Properties: Comment: "MOS Practice Exam" and Category: "Excel 365".
B8: 3 | C8: Import the "Old Town Sales-Alternate" Excel file into a new worksheet named "Alternate". Make it the last worksheet.
B9: 4 | C9: Rotate the headings on the Alternate worksheet counterclockwise 90°. Set the column width to 8.0 for columns B:E.
B10: 5 | C10: In one step, go to the OldTownStore name range. Put a Green, Accent 6, Darker 50% thick border around the selected cells.
B11: 6 | C11: Unhide the "Project 2" worksheet.
B12: 7 | C12: Complete the tasks for all Projects (1-7). The instructions for each worksheet will be at the top of the worksheet.
B13: 8 | C13: When you have completed all tasks, please save and close the workbook.

Sheet Project 1
C2: Complete all tasks below on the Project 1 Worksheet.
B3: 1 | C3: Convert the Online Sales data (C12:G29) to a Table. Name the table "Online2022".
B4: 2 | C4: Customize the ribbon by adding the Draw tab.
B5: 3 | C5: Add the Total row and calculate the average Products Price. Apply Table Style, Blue Table Style Medium 20.
B6: 4 | C6: Format the Price column as Currency.
B7: 5 | C7: Sum the Quantity column in the total row.
C10: Online Sales During Buy 1 Get 1 Free Sale
C12: Date | D12: Quantity | E12: Item | F12: Price (ea.) | G12: State
C13: 42581 | D13: 6 | E13: Old Bay | F13: 1.99 | G13: MD
C14: 42581 | D14: 12 | E14: Original Blend | F14: 2.79 | G14: OH
C15: 42581 | D15: 4 | E15: Original Blend | F15: 2.79 | G15: CA
C16: 42581 | D16: 8 | E16: Sea Salt and Caramel | F16: 5.99 | G16: MO
C17: 42581 | D17: 5 | E17: Sea Salt and Caramel | F17: 5.99 | G17: NJ
C18: 42581 | D18: 8 | E18: Truffle | F18: 7.69 | G18: VA
C19: 42581 | D19: 2 | E19: Truffle | F19: 7.69 | G19: DC
C20: 42581 | D20: 2 | E20: Original Blend | F20: 2.79 | G20: AL
C21: 42581 | D21: 4 | E21: Old Bay | F21: 1.99 | G21: MD
C22: 42581 | D22: 14 | E22: Truffle | F22: 7.69 | G22: DC
C23: 42581 | D23: 8 | E23: Sea Salt and Caramel | F23: 5.99 | G23: MS
C24: 42581 | D24: 10 | E24: Original Blend | F24: 2.79 | G24: NC
... C29: 42582 | D29: 2 | E29: Old Bay | F29: 1.99 | G29: ID

Sheet Project 2
C2: Complete task 1 on the on the project 2 Worksheet.
B3: 1 | C3: Open a new window of the workbook. Show the Lookup Tables sheet in the new window. Arrange vertically.
C4: You should be seeing two windows of this workbook, one showing the Project 2 worksheet and the other the Lookup Tables worksheet
C5: Complete all tasks below on the Lookup Tables Worksheet.
B6: 2 | C6: For Cells (K6:P19), apply a Thick Outside Border.
B7: 3 | C7: In cell C3 on the Lookup Tables sheet, create a hyperlink to cell C11 on the Project 2 sheet with the text "Jump to Instructions".
B8: 4 | C8: Add spelling checker to the quick access tool bar.
B9: 5 | C9: Run the spellchecker from the quick access tool bar. Correct any mistakes found on the sheet. Sabi is correct.
B10: 6 | C10: Display all formulas on the worksheet.
B11: 7 | C11: Save the workbook showing the Lookup Tables sheet.
B12: 8 | C12: Close this window that has the Project 2 instructions showing, then use the hyperlink to jump to Project 2.

Sheet Project 3
C2: Complete all tasks below on the Project 3 Worksheet.
B3: 1 | C3: Apply the Title cell style to cell C11.
B4: 2 | C4: Apply the Blue, Accent 1, Darker 50% fill color to cell C11.
B5: 3 | C5: Apply the White, Background 1 font color to cell C11.
B6: 4 | C6: Merge and Center the worksheet title across cells C11:G11.
B7: 5 | C7: Apply the Heading 1 cell style to cell D12 and Merge and Center cells D12:G12
B8: 6 | C8: Apply the Accounting Number Format with 0 digits after the decimal to cells D14:G16.
B9: 7 | C9: Enter the word "Total" in cell C17 and use a Function to calculate the totals of cells in columns D through G.
C11: Premier Chocolates Sales (August)
D12: Truck Location
D13: Farragut Square | E13: George Washington | F13: Georgetown | G13: K Street
C14: Old Bay | D14: 2500 | E14: 900 | F14: 800 | G14: 1150
C15: Truffle | D15: 2760 | E15: 525 | F15: 1005 | G15: 2100
C16: Sea Salt and Caramel | D16: 3800 | E16: 1800 | F16: 1225 | G16: 2010

Sheet Project 4
C2: Complete all tasks below on the Project 4 Worksheet.
B3: 1 | C3: Insert a Clustered Column Chart to show not only product sales by location, but also the total sales.
B4: 2 | C4: Move the chart where the upper left corner of the chart is in the upper left corner of cell C19.
B5: 3 | C5: Change the Chart Title to "Premier Chocolates Sales (August)".
B6: 4 | C6: Use Conditional Formatting to apply Light Red Fill with Dark Red Text to chocolate sales that exceed 1000 (do not include Total amount).
C11: Premier Chocolates Sales (August)
D12: Truck Location
D13: Farragut Square | E13: George Washington | F13: Georgetown | G13: K Street
C14: Old Bay | D14: 2500 | E14: 900 | F14: 800 | G14: 1150
C15: Truffle | D15: 2760 | E15: 525 | F15: 1005 | G15: 2100
C16: Sea Salt and Caramel | D16: 3800 | E16: 1800 | F16: 1225 | G16: 2010
C17: Total | D17: =SUM(D14:D16) -> 9060 | E17: =SUM(E14:E16) -> 3225 | F17: =SUM(F14:F16) -> 3030 | G17: =SUM(G14:G16) -> 5260

Sheet Project 5
C2: Complete all tasks below on the Project 5 Worksheet.
B3: 1 | C3: Select cells C13:C43 and apply the Short Date format.
B4: 2 | C4: Type Average in cell B44.
B5: 3 | C5: Calculate the average number of chocolates sold in cells D44:F44. Select Number format and no numbers after the decimal.
B6: 4 | C6: For cells D13:F43 use Conditional Formatting to apply a green fill with dark green text to the values that exceed the averages (by column).
B7: 5 | C7: In cell H13, enter a formula to calculate the daily total in dollars. Use the current price per box in cell M12.
B8: 6 | C8: In the formula in cell H13, use absolute references where appropriate and copy the formula down the column to H43.
B9: 7 | C9: In cell I13, enter a formula using the IF function to determine whether the daily sales goal in cell M13 was met. Display a "Yes" or "No."
B10: 8 | C10: Copy the formula in cell I13 down the column to I43.
C12: Date | D12: Old Bay | E12: Black Truffle | F12: Sea Salt and Caramel | G12: Daily Total (# sold) | H12: Daily Total ($) | I12: Sales Goal Met? | K12: w/Price Increase | L12: Current price per box: | M12: 5
C13: 42583 | D13: 42 | E13: 115 | F13: 92 | G13: =SUM(D13:F13) -> 249 | K13: =G13*NewPrice -> 1245 | L13: Daily sales goal: | M13: 1250
C14: 42584 | D14: 42 | E14: 42 | F14: 117 | G14: =SUM(D14:F14) -> 201 | K14: =G14*NewPrice -> 1005 | L14: Average daily sales:
C15: 42585 | D15: 105 | E15: 124 | F15: 64 | G15: =SUM(D15:F15) -> 293 | K15: =G15*NewPrice -> 1465 | L15: Lowest daily sales:
C16: 42586 | D16: 141 | E16: 83 | F16: 76 | G16: =SUM(D16:F16) -> 300 | K16: =G16*NewPrice -> 1500 | L16: Highest daily sales:
C17: 42587 | D17: 137 | E17: 73 | F17: 109 | G17: =SUM(D17:F17) -> 319 | K17: =G17*NewPrice -> 1595
C18: 42588 | D18: 68 | E18: 44 | F18: 60 | G18: =SUM(D18:F18) -> 172 | K18: =G18*NewPrice -> 860 | L18: New target daily sales goal: | M18: =AVERAGE(K13:K43) -> 1324.8387
C19: 42589 | D19: 82 | E19: 58 | F19: 145 | G19: =SUM(D19:F19) -> 285 | K19: =G19*NewPrice -> 1425 | L19: New price per box: | M19: 5
C20: 42590 | D20: 125 | E20: 96 | F20: 92 | G20: =SUM(D20:F20) -> 313 | K20: =G20*NewPrice -> 1565
C21: 42591 | D21: 20 | E21: 26 | F21: 39 | G21: =SUM(D21:F21) -> 85 | K21: =G21*NewPrice -> 425 | L21: Lookup date:
C22: 42592 | D22: 67 | E22: 38 | F22: 21 | G22: =SUM(D22:F22) -> 126 | K22: =G22*NewPrice -> 630 | L22: Sales goal met?
C23: 42593 | D23: 121 | E23: 124 | F23: 132 | G23: =SUM(D23:F23) -> 377 | K23: =G23*NewPrice -> 1885
C24: 42594 | D24: 140 | E24: 76 | F24: 25 | G24: =SUM(D24:F24) -> 241 | K24: =G24*NewPrice -> 1205
C25: 42595 | D25: 147 | E25: 77 | F25: 77 | G25: =SUM(D25:F25) -> 301 | K25: =G25*NewPrice -> 1505
C26: 42596 | D26: 86 | E26: 128 | F26: 59 | G26: =SUM(D26:F26) -> 273 | K26: =G26*NewPrice -> 1365
C27: 42597 | D27: 50 | E27: 122 | F27: 96 | G27: =SUM(D27:F27) -> 268 | K27: =G27*NewPrice -> 1340
C28: 42598 | D28: 80 | E28: 92 | F28: 139 | G28: =SUM(D28:F28) -> 311 | K28: =G28*NewPrice -> 1555
C29: 42599 | D29: 41 | E29: 69 | F29: 59 | G29: =SUM(D29:F29) -> 169 | K29: =G29*NewPrice -> 845
C30: 42600 | D30: 26 | E30: 38 | F30: 125 | G30: =SUM(D30:F30) -> 189 | K30: =G30*NewPrice -> 945
C31: 42601 | D31: 93 | E31: 41 | F31: 133 | G31: =SUM(D31:F31) -> 267 | K31: =G31*NewPrice -> 1335
C32: 42602 | D32: 84 | E32: 144 | F32: 146 | G32: =SUM(D32:F32) -> 374 | K32: =G32*NewPrice -> 1870
C33: 42603 | D33: 25 | E33: 124 | F33: 145 | G33: =SUM(D33:F33) -> 294 | K33: =G33*NewPrice -> 1470
C34: 42604 | D34: 107 | E34: 60 | F34: 142 | G34: =SUM(D34:F34) -> 309 | K34: =G34*NewPrice -> 1545
... C43: 42613 | D43: 125 | E43: 39 | F43: 80 | G43: =SUM(D43:F43) -> 244 | K43: =G43*NewPrice -> 1220

Sheet Project 6
C2: Complete all tasks below on the Project 6 Worksheet.
B3: 1 | C3: Select cells G12:G42 and name the range DailySales.
B4: 2 | C4: In cell M13, enter a formula using the named range DailySales to calculate the Average daily sales in dollars.
B5: 3 | C5: In cell M14, enter a formula using the named range DailySales to calculate the Lowest daily sales in dollars.
B6: 4 | C6: In cell M15, enter a formula using the named range DailySales to calculate the Highest daily sales in dollars.
C11: Date | D11: Old Bay | E11: Black Truffle | F11: Sea Salt and Caramel | G11: Daily Total (# sold) | H11: Daily Total ($) | I11: Sales Goal Met? | K11: w/Price Increase | L11: Current price per box: | M11: 6
C12: 42583 | D12: 36 | E12: 80 | F12: 22 | G12: =SUM(D12:F12) -> 138 | H12: =G12*$M$11 -> 828 | I12: =IF(H12>=$M$12,"Yes","No") -> No | K12: =G12*NewPrice -> 0 | L12: Daily sales goal: | M12: 1250
C13: 42584 | D13: 45 | E13: 97 | F13: 114 | G13: =SUM(D13:F13) -> 256 | H13: =G13*$M$11 -> 1536 | I13: =IF(H13>=$M$12,"Yes","No") -> Yes | K13: =G13*NewPrice -> 0 | L13: Average daily sales:
C14: 42585 | D14: 79 | E14: 75 | F14: 105 | G14: =SUM(D14:F14) -> 259 | H14: =G14*$M$11 -> 1554 | I14: =IF(H14>=$M$12,"Yes","No") -> Yes | K14: =G14*NewPrice -> 0 | L14: Lowest daily sales:
C15: 42586 | D15: 101 | E15: 109 | F15: 69 | G15: =SUM(D15:F15) -> 279 | H15: =G15*$M$11 -> 1674 | I15: =IF(H15>=$M$12,"Yes","No") -> Yes | K15: =G15*NewPrice -> 0 | L15: Highest daily sales:
C16: 42587 | D16: 52 | E16: 97 | F16: 84 | G16: =SUM(D16:F16) -> 233 | H16: =G16*$M$11 -> 1398 | I16: =IF(H16>=$M$12,"Yes","No") -> Yes | K16: =G16*NewPrice -> 0
C17: 42588 | D17: 20 | E17: 31 | F17: 72 | G17: =SUM(D17:F17) -> 123 | H17: =G17*$M$11 -> 738 | I17: =IF(H17>=$M$12,"Yes","No") -> No | K17: =G17*NewPrice -> 0 | L17: New target daily sales goal: | M17: =AVERAGE(K12:K42) -> 0
C18: 42589 | D18: 48 | E18: 99 | F18: 27 | G18: =SUM(D18:F18) -> 174 | H18: =G18*$M$11 -> 1044 | I18: =IF(H18>=$M$12,"Yes","No") -> No | K18: =G18*NewPrice -> 0 | L18: New price per box:
C19: 42590 | D19: 19 | E19: 145 | F19: 83 | G19: =SUM(D19:F19) -> 247 | H19: =G19*$M$11 -> 1482 | I19: =IF(H19>=$M$12,"Yes","No") -> Yes | K19: =G19*NewPrice -> 0
C20: 42591 | D20: 122 | E20: 128 | F20: 46 | G20: =SUM(D20:F20) -> 296 | H20: =G20*$M$11 -> 1776 | I20: =IF(H20>=$M$12,"Yes","No") -> Yes | K20: =G20*NewPrice -> 0
C21: 42592 | D21: 77 | E21: 142 | F21: 102 | G21: =SUM(D21:F21) -> 321 | H21: =G21*$M$11 -> 1926 | I21: =IF(H21>=$M$12,"Yes","No") -> Yes | K21: =G21*NewPrice -> 0
C22: 42593 | D22: 89 | E22: 145 | F22: 103 | G22: =SUM(D22:F22) -> 337 | H22: =G22*$M$11 -> 2022 | I22: =IF(H22>=$M$12,"Yes","No") -> Yes | K22: =G22*NewPrice -> 0
C23: 42594 | D23: 115 | E23: 146 | F23: 19 | G23: =SUM(D23:F23) -> 280 | H23: =G23*$M$11 -> 1680 | I23: =IF(H23>=$M$12,"Yes","No") -> Yes | K23: =G23*NewPrice -> 0
C24: 42595 | D24: 147 | E24: 133 | F24: 59 | G24: =SUM(D24:F24) -> 339 | H24: =G24*$M$11 -> 2034 | I24: =IF(H24>=$M$12,"Yes","No") -> Yes | K24: =G24*NewPrice -> 0
C25: 42596 | D25: 41 | E25: 125 | F25: 59 | G25: =SUM(D25:F25) -> 225 | H25: =G25*$M$11 -> 1350 | I25: =IF(H25>=$M$12,"Yes","No") -> Yes | K25: =G25*NewPrice -> 0
C26: 42597 | D26: 70 | E26: 59 | F26: 96 | G26: =SUM(D26:F26) -> 225 | H26: =G26*$M$11 -> 1350 | I26: =IF(H26>=$M$12,"Yes","No") -> Yes | K26: =G26*NewPrice -> 0
C27: 42598 | D27: 25 | E27: 139 | F27: 149 | G27: =SUM(D27:F27) -> 313 | H27: =G27*$M$11 -> 1878 | I27: =IF(H27>=$M$12,"Yes","No") -> Yes | K27: =G27*NewPrice -> 0
C28: 42599 | D28: 26 | E28: 96 | F28: 68 | G28: =SUM(D28:F28) -> 190 | H28: =G28*$M$11 -> 1140 | I28: =IF(H28>=$M$12,"Yes","No") -> No | K28: =G28*NewPrice -> 0
C29: 42600 | D29: 93 | E29: 59 | F29: 112 | G29: =SUM(D29:F29) -> 264 | H29: =G29*$M$11 -> 1584 | I29: =IF(H29>=$M$12,"Yes","No") -> Yes | K29: =G29*NewPrice -> 0
C30: 42601 | D30: 21 | E30: 77 | F30: 131 | G30: =SUM(D30:F30) -> 229 | H30: =G30*$M$11 -> 1374 | I30: =IF(H30>=$M$12,"Yes","No") -> Yes | K30: =G30*NewPrice -> 0
... C42: 42613 | D42: 39 | E42: 92 | F42: 80 | G42: =SUM(D42:F42) -> 211 | H42: =G42*$M$11 -> 1266 | I42: =IF(H42>=$M$12,"Yes","No") -> Yes | K42: =G42*NewPrice -> 0

Sheet Project 7
C1: Missing Newsletter
C2: Total Enrolled
C3: Studied Abroad
C6: The Roux Academy of Art
C9: Student Roster 2017
A10: id | B10: last | C10: first | D10: state | E10: phone | F10: email | G10: gpa | H10: program | I10: studiedabroad | J10: studiedin | K10: newsletter
A11: 5 | B11: Kirby | C11: An | D11: Texas | E11: (806) 555-5527 | F11: akirby@alumni.rouxacademy.com | G11: 3.19 | H11: Fine Art and Visual Culture | I11: NO | K11: NO
A12: 91 | B12: Gomez | C12: Mirta | D12: Ohio | E12: (937) 555-9986 | F12: mgomez@alumni.rouxacademy.com | G12: 2.09 | H12: Animation | I12: YES | J12: Thailand | K12: YES
A13: 184 | B13: Cook | C13: Alana | D13: Iowa | E13: (319) 555-0182 | F13: acook2@alumni.rouxacademy.com | G13: 3.64 | H13: Graphic Design | I13: NO | K13: YES
A14: 318 | B14: Lara | C14: Magdalena | D14: Virginia | E14: (434) 555-8004 | F14: mlara3@alumni.rouxacademy.com | G14: 3.39 | H14: Graphic Design | I14: NO | K14: YES
A15: 434 | B15: Jefferson | C15: Kirstin | D15: Massachusetts | E15: (978) 555-6967 | F15: kjefferson@alumni.rouxacademy.com | G15: 3.75 | H15: Graphic Design | I15: NO | K15: NO
A16: 437 | B16: Montoya | C16: Deandre | D16: Louisiana | E16: (504) 555-8873 | F16: dmontoya2@alumni.rouxacademy.com | G16: 2.48 | H16: Animation | I16: NO | K16: NO
A17: 443 | B17: Rodriguez | C17: Emile | D17: Illinois | E17: (217) 555-6858 | F17: erodriguez@alumni.rouxacademy.com | G17: 3.23 | H17: Graphic Design | I17: NO | K17: YES
A18: 447 | B18: Lindsey | C18: Tomi | D18: Louisiana | E18: (318) 555-7067 | F18: tlindsey3@alumni.rouxacademy.com | G18: 2.47 | H18: Fashion and Textile Design | I18: NO | K18: NO
A19: 453 | B19: Hyde | C19: Jewell | D19: Wisconsin | E19: (534) 555-4904 | F19: jhyde@alumni.rouxacademy.com | G19: 3.08 | H19: Fashion and Textile Design | I19: NO | K19: NO
A20: 471 | B20: Maldonado | C20: Frederic | D20: Virginia | E20: (540) 555-9021 | F20: fmaldonado@alumni.rouxacademy.com | G20: 3.44 | H20: Fashion and Textile Design | I20: YES | J20: Spain | K20: YES
A21: 500 | B21: Conley | C21: Sonja | D21: New York | E21: (315) 555-7293 | F21: sconley3@alumni.rouxacademy.com | G21: 3.03 | H21: Animation | I21: NO | K21: NO
A22: 506 | B22: Parsons | C22: Rudolf | D22: Texas | E22: (281) 555-4112 | F22: rparsons@alumni.rouxacademy.com | G22: 3.61 | H22: Fine Art and Visual Culture | I22: NO | K22: NO
A23: 549 | B23: Eaton | C23: Fredda | D23: Arkansas | E23: (501) 555-4686 | F23: featon@alumni.rouxacademy.com | G23: 2.53 | H23: Graphic Design | I23: YES | J23: Thailand | K23: YES
A24: 561 | B24: England | C24: Santana | D24: Minnesota | E24: (612) 555-6583 | F24: sengland@alumni.rouxacademy.com | G24: 2.76 | H24: Graphic Design | I24: NO | K24: NO
A25: 594 | B25: Gilliam | C25: Janna | D25: Kentucky | E25: (502) 555-3168 | F25: jgilliam2@alumni.rouxacademy.com | G25: 3.23 | H25: Graphic Design | I25: YES | J25: Russia | K25: NO
A26: 627 | B26: Knowles | C26: Elayne | D26: Missouri | E26: (636) 555-7056 | F26: eknowles2@alumni.rouxacademy.com | G26: 3.7 | H26: Fine Art and Visual Culture | I26: NO | K26: YES
A27: 689 | B27: Waters | C27: Carter | D27: New Jersey | E27: (201) 555-7678 | F27: cwaters2@alumni.rouxacademy.com | G27: 3.52 | H27: Fine Art and Visual Culture | I27: NO | K27: YES
A28: 776 | B28: Travis | C28: Lidia | D28: Minnesota | E28: (218) 555-6969 | F28: ltravis@alumni.rouxacademy.com | G28: 3.98 | H28: Graphic Design | I28: NO | K28: YES
A29: 803 | B29: Pratt | C29: Robert | D29: California | E29: (323) 555-4034 | F29: rpratt2@alumni.rouxacademy.com | G29: 3.2 | H29: Graphic Design | I29: NO | K29: YES
A30: 826 | B30: Reyes | C30: Naomi | D30: Utah | E30: (435) 555-1991 | F30: nreyes@alumni.rouxacademy.com | G30: 2.07 | H30: Animation | I30: NO | K30: NO
A31: 998 | B31: Cochran | C31: Nickie | D31: California | E31: (424) 555-7152 | F31: ncochran@alumni.rouxacademy.com | G31: 3.6 | H31: Fashion and Textile Design | I31: NO | K31: NO
A32: 1022 | B32: Moran | C32: Sallie | D32: Ohio | E32: (330) 555-1897 | F32: smoran3@alumni.rouxacademy.com | G32: 2.34 | H32: Animation | I32: NO | K32: NO
A33: 1034 | B33: Church | C33: Mackenzie | D33: California | E33: (530) 555-7087 | F33: mchurch@alumni.rouxacademy.com | G33: 2.6 | H33: Animation | I33: NO | K33: YES
A34: 1074 | B34: Weaver | C34: Blake | D34: Michigan | E34: (586) 555-9771 | F34: bweaver2@alumni.rouxacademy.com | G34: 2.21 | H34: Graphic Design | I34: NO | K34: YES
A35: 1104 | B35: Torres | C35: Ricki | D35: Florida | E35: (407) 555-0973 | F35: rtorres4@alumni.rouxacademy.com | G35: 3.53 | H35: Animation | I35: NO | K35: NO
A36: 1159 | B36: Snow | C36: Launa | D36: Virginia | E36: (540) 555-1460 | F36: lsnow@alumni.rouxacademy.com | G36: 2.6 | H36: Fine Art and Visual Culture | I36: NO | K36: NO
A37: 1184 | B37: Lott | C37: Blaine | D37: California | E37: (559) 555-9196 | F37: blott@alumni.rouxacademy.com | G37: 3.72 | H37: Graphic Design | I37: NO | K37: YES
A38: 1261 | B38: Velez | C38: Leonora | D38: Connecticut | E38: (860) 555-5640 | F38: lvelez3@alumni.rouxacademy.com | G38: 2.24 | H38: Graphic Design | I38: YES | J38: India | K38: YES
A39: 1298 | B39: Becker | C39: Young | D39: South Carolina | E39: (803) 555-8489 | F39: ybecker2@alumni.rouxacademy.com | G39: 3.95 | H39: Fashion and Textile Design | I39: NO | K39: NO
A40: 1375 | B40: Cantrell | C40: Emily | D40: California | E40: (415) 555-4641 | F40: ecantrell2@alumni.rouxacademy.com | G40: 3.9 | H40: Animation | I40: NO | K40: YES
A41: 1406 | B41: Lowe | C41: Harold | D41: Florida | E41: (305) 555-6525 | F41: hlowe@alumni.rouxacademy.com | G41: 2.41 | H41: Animation | I41: NO | K41: NO
A42: 1669 | B42: Walls | C42: Loria | D42: Maryland | E42: (301) 555-7093 | F42: lwalls@alumni.rouxacademy.com | G42: 3.28 | H42: Graphic Design | I42: YES | J42: Lebanon | K42: NO
A43: 1672 | B43: Huff | C43: Jin | D43: New York | E43: (607) 555-9702 | F43: jhuff@alumni.rouxacademy.com | G43: 3.32 | H43: Fine Art and Visual Culture | I43: NO | K43: YES
A44: 1687 | B44: Vazquez | C44: Werner | D44: Delaware | E44: (302) 555-8969 | F44: wvazquez@alumni.rouxacademy.com | G44: 3.33 | H44: Fashion and Textile Design | I44: NO | K44: YES
A45: 1735 | B45: Jenkins | C45: Marion | D45: Michigan | E45: (517) 555-0252 | F45: mjenkins5@alumni.rouxacademy.com | G45: 3.61 | H45: Graphic Design | I45: NO | K45: NO
A46: 1858 | B46: Washington | C46: Mitzie | D46: Maryland | E46: (240) 555-2358 | F46: mwashington3@alumni.rouxacademy.com | G46: 2.51 | H46: Fashion and Textile Design | I46: NO | K46: YES
A47: 1909 | B47: Webb | C47: Addie | D47: Louisiana | E47: (318) 555-9192 | F47: awebb2@alumni.rouxacademy.com | G47: 2.43 | H47: Graphic Design | I47: NO | K47: NO
A48: 1912 | B48: James | C48: Arline | D48: California | E48: (916) 555-2333 | F48: ajames@alumni.rouxacademy.com | G48: 2.98 | H48: Graphic Design | I48: YES | J48: China | K48: NO
A49: 1967 | B49: Frazier | C49: Marget | D49: New York | E49: (845) 555-9009 | F49: mfrazier@alumni.rouxacademy.com | G49: 3.24 | H49: Fine Art and Visual Culture | I49: NO | K49: YES
A50: 1996 | B50: Trujillo | C50: Bianca | D50: Indiana | E50: (317) 555-2644 | F50: btrujillo@alumni.rouxacademy.com | G50: 3.08 | H50: Fine Art and Visual Culture | I50: NO | K50: NO
A51: 2001 | B51: Cunningham | C51: William | D51: Massachusetts | E51: (781) 555-5971 | F51: wcunningham@alumni.rouxacademy.com | G51: 2.12 | H51: Graphic Design | I51: NO | K51: NO
A52: 2108 | B52: Day | C52: Cesar | D52: Maryland | E52: (443) 555-8218 | F52: cday@alumni.rouxacademy.com | G52: 3.97 | H52: Graphic Design | I52: NO | K52: NO
A53: 2139 | B53: Ross | C53: Ria | D53: Louisiana | E53: (985) 555-1871 | F53: rross@alumni.rouxacademy.com | G53: 3.62 | H53: Animation | I53: YES | J53: Brazil | K53: YES
A54: 2158 | B54: Robertson | C54: Collette | D54: South Carolina | E54: (843) 555-9323 | F54: crobertson@alumni.rouxacademy.com | G54: 2.47 | H54: Fine Art and Visual Culture | I54: YES | J54: Poland | K54: YES
A55: 2166 | B55: Moreno | C55: Zula | D55: Georgia | E55: (229) 555-9442 | F55: zmoreno2@alumni.rouxacademy.com | G55: 2.37 | H55: Animation | I55: NO | K55: YES
A56: 2201 | B56: Owens | C56: Maisie | D56: Colorado | E56: (303) 555-1777 | F56: mowens@alumni.rouxacademy.com | G56: 3.59 | H56: Animation | I56: NO | K56: YES
A57: 2335 | B57: Lawrence | C57: Lyndsey | D57: Florida | E57: (386) 555-8382 | F57: llawrence@alumni.rouxacademy.com | G57: 3.13 | H57: Animation | I57: NO | K57: NO
A58: 2340 | B58: Maxwell | C58: Beatriz | D58: Missouri | E58: (314) 555-4214 | F58: bmaxwell@alumni.rouxacademy.com | G58: 2.13 | H58: Animation | I58: NO | K58: YES
A59: 2426 | B59: Snow | C59: Graham | D59: California | E59: (650) 555-6739 | F59: gsnow@alumni.rouxacademy.com | G59: 2.73 | H59: Graphic Design | I59: NO | K59: NO
A60: 2478 | B60: Vance | C60: Arlene | D60: Arkansas | E60: (870) 555-5117 | F60: avance2@alumni.rouxacademy.com | G60: 2.84 | H60: Fashion and Textile Design | I60: NO | K60: NO
A61: 2479 | B61: Barnett | C61: Erwin | D61: Washington | E61: (360) 555-0325 | F61: ebarnett@alumni.rouxacademy.com | G61: 3.66 | H61: Fine Art and Visual Culture | I61: NO | K61: YES
A62: 2515 | B62: Mcintosh | C62: Tiffani | D62: California | E62: (530) 555-1751 | F62: tmcintosh@alumni.rouxacademy.com | G62: 2.98 | H62: Graphic Design | I62: NO | K62: NO
A63: 2545 | B63: Crosby | C63: Mimi | D63: Minnesota | E63: (218) 555-3213 | F63: mcrosby2@alumni.rouxacademy.com | G63: 2.12 | H63: Fine Art and Visual Culture | I63: NO | K63: YES
A64: 2594 | B64: Lawrence | C64: Mee | D64: Massachusetts | E64: (508) 555-2712 | F64: mlawrence3@alumni.rouxacademy.com | G64: 3.43 | H64: Fine Art and Visual Culture | I64: YES | J64: India | K64: NO
A65: 2648 | B65: Franklin | C65: Rosario | D65: Vermont | E65: (802) 555-0021 | F65: rfranklin2@alumni.rouxacademy.com | G65: 2.99 | H65: Fashion and Textile Design | I65: YES | J65: Greece | K65: NO
A66: 2969 | B66: Riddle | C66: Sandee | D66: Missouri | E66: (573) 555-6701 | F66: sriddle@alumni.rouxacademy.com | G66: 3.45 | H66: Graphic Design | I66: NO | K66: YES
A67: 3055 | B67: Farmer | C67: Tandra | D67: Hawaii | E67: (808) 555-3228 | F67: tfarmer@alumni.rouxacademy.com | G67: 2.02 | H67: Fashion and Textile Design | I67: NO | K67: YES
A68: 3064 | B68: Tate | C68: Aurelia | D68: New Jersey | E68: (732) 555-0564 | F68: atate@alumni.rouxacademy.com | G68: 2.31 | H68: Graphic Design | I68: NO | K68: YES
A69: 3180 | B69: Vargas | C69: Margie | D69: Washington | E69: (206) 555-9416 | F69: mvargas2@alumni.rouxacademy.com | G69: 3.67 | H69: Graphic Design | I69: NO | K69: NO
A70: 3187 | B70: Moon | C70: Demetra | D70: Pennsylvania | E70: (570) 555-5162 | F70: dmoon3@alumni.rouxacademy.com | G70: 2.85 | H70: Animation | I70: NO | K70: YES
A71: 3213 | B71: Barrera | C71: Nicolle | D71: California | E71: (408) 555-1532 | F71: nbarrera@alumni.rouxacademy.com | G71: 2.43 | H71: Animation | I71: NO | K71: YES
A72: 3217 | B72: Robinson | C72: Monnie | D72: Georgia | E72: (706) 555-0343 | F72: mrobinson5@alumni.rouxacademy.com | G72: 3.83 | H72: Fashion and Textile Design | I72: NO | K72: YES
A73: 3242 | B73: Wynn | C73: Toccara | D73: New Jersey | E73: (856) 555-6850 | F73: twynn@alumni.rouxacademy.com | G73: 2.07 | H73: Fashion and Textile Design | I73: YES | J73: Turkey | K73: NO
A74: 3276 | B74: Macdonald | C74: Eileen | D74: Michigan | E74: (313) 555-9400 | F74: emacdonald@alumni.rouxacademy.com | G74: 3.98 | H74: Animation | I74: NO | K74: YES
A75: 3371 | B75: Fowler | C75: Amparo | D75: Missouri | E75: (660) 555-8707 | F75: afowler@alumni.rouxacademy.com | G75: 2.8 | H75: Fashion and Textile Design | I75: NO | K75: NO
A76: 3393 | B76: Skinner | C76: Coralie | D76: California | E76: (805) 555-9494 | F76: cskinner@alumni.rouxacademy.com | G76: 2.36 | H76: Fine Art and Visual Culture | I76: YES | J76: France | K76: YES
A77: 3460 | B77: Mcpherson | C77: Elenora | D77: New York | E77: (929) 555-8001 | F77: emcpherson@alumni.rouxacademy.com | G77: 3.87 | H77: Animation | I77: NO | K77: YES
A78: 3569 | B78: Lambert | C78: Shani | D78: Texas | E78: (325) 555-3547 | F78: slambert2@alumni.rouxacademy.com | G78: 3.54 | H78: Graphic Design | I78: YES | J78: Brazil | K78: YES
A79: 3582 | B79: Blackwell | C79: Wilburn | D79: Texas | E79: (254) 555-1995 | F79: wblackwell@alumni.rouxacademy.com | G79: 3.02 | H79: Animation | I79: NO | K79: YES
A80: 3605 | B80: Jarvis | C80: Owen | D80: Georgia | E80: (912) 555-1844 | F80: ojarvis@alumni.rouxacademy.com | G80: 3.12 | H80: Graphic Design | I80: NO | K80: NO
A81: 3648 | B81: Kramer | C81: Louella | D81: Alabama | E81: (205) 555-5151 | F81: lkramer3@alumni.rouxacademy.com | G81: 3.21 | H81: Animation | I81: NO | K81: YES
A82: 3672 | B82: Russo | C82: Gussie | D82: Illinois | E82: (312) 555-5497 | F82: grusso4@alumni.rouxacademy.com | G82: 3.31 | H82: Animation | I82: YES | J82: Lebanon | K82: YES
A83: 3728 | B83: Cohen | C83: Sheilah | D83: Oklahoma | E83: (918) 555-0272 | F83: scohen@alumni.rouxacademy.com | G83: 3.73 | H83: Fashion and Textile Design | I83: NO | K83: NO
A84: 3749 | B84: Rivera | C84: Jonnie | D84: Florida | E84: (386) 555-7088 | F84: jrivera@alumni.rouxacademy.com | G84: 3.92 | H84: Graphic Design | I84: NO | K84: YES
A85: 3757 | B85: Finch | C85: Hong | D85: Florida | E85: (954) 555-5125 | F85: hfinch@alumni.rouxacademy.com | G85: 2.48 | H85: Animation | I85: NO | K85: YES
A86: 3772 | B86: Walker | C86: Leota | D86: California | E86: (657) 555-8873 | F86: lwalker4@alumni.rouxacademy.com | G86: 3.35 | H86: Animation | I86: NO | K86: NO
A87: 3778 | B87: Mccarthy | C87: Napoleon | D87: Iowa | E87: (641) 555-8658 | F87: nmccarthy@alumni.rouxacademy.com | G87: 2.05 | H87: Animation | I87: NO | K87: NO
A88: 3786 | B88: Solis | C88: Kecia | D88: Washington | E88: (360) 555-8019 | F88: ksolis@alumni.rouxacademy.com | G88: 3.62 | H88: Fine Art and Visual Culture | I88: YES | J88: Mexico | K88: YES
A89: 3788 | B89: Brennan | C89: Nickole | D89: Minnesota | E89: (763) 555-8344 | F89: nbrennan2@alumni.rouxacademy.com | G89: 2.26 | H89: Fashion and Textile Design | I89: NO | K89: YES
A90: 3874 | B90: Weber | C90: Regine | D90: Texas | E90: (325) 555-8298 | F90: rweber@alumni.rouxacademy.com | G90: 3.42 | H90: Fine Art and Visual Culture | I90: NO | K90: NO
A91: 4141 | B91: Becker | C91: Clark | D91: Minnesota | E91: (507) 555-4592 | F91: cbecker@alumni.rouxacademy.com | G91: 2.34 | H91: Fine Art and Visual Culture | I91: YES | J91: Greece | K91: NO
A92: 4145 | B92: Farmer | C92: Corrine | D92: Texas | E92: (325) 555-6811 | F92: cfarmer2@alumni.rouxacademy.com | G92: 3.56 | H92: Graphic Design | I92: NO | K92: YES
A93: 4195 | B93: Waters | C93: Millie | D93: Oregon | E93: (503) 555-6588 | F93: mwaters2@alumni.rouxacademy.com | G93: 2.67 | H93: Fashion and Textile Design | I93: NO | K93: NO
A94: 4213 | B94: Byers | C94: Mitchell | D94: Indiana | E94: (219) 555-0191 | F94: mbyers3@alumni.rouxacademy.com | G94: 3.5 | H94: Fashion and Textile Design | I94: YES | J94: Germany | K94: YES
A95: 4267 | B95: Lee | C95: Monroe | D95: Arizona | E95: (602) 555-1099 | F95: mlee3@alumni.rouxacademy.com | G95: 3.4 | H95: Fine Art and Visual Culture | I95: NO | K95: NO
A96: 4343 | B96: Collier | C96: Louella | D96: Arizona | E96: (623) 555-7749 | F96: lcollier@alumni.rouxacademy.com | G96: 3.21 | H96: Animation | I96: NO | K96: YES
A97: 4392 | B97: Mueller | C97: Leslie | D97: Georgia | E97: (706) 555-8810 | F97: lmueller2@alumni.rouxacademy.com | G97: 2.51 | H97: Graphic Design | I97: NO | K97: NO
A98: 4429 | B98: Buckley | C98: Sun | D98: Colorado | E98: (720) 555-7142 | F98: sbuckley2@alumni.rouxacademy.com | G98: 3.5 | H98: Animation | I98: NO | K98: YES
A99: 4450 | B99: Alexander | C99: Marlon | D99: Virginia | E99: (703) 555-3539 | F99: malexander5@alumni.rouxacademy.com | G99: 2 | H99: Fine Art and Visual Culture | I99: NO | K99: YES
A100: 4473 | B100: Graves | C100: Nereida | D100: Florida | E100: (813) 555-6661 | F100: ngraves@alumni.rouxacademy.com | G100: 2.55 | H100: Graphic Design | I100: NO | K100: YES
A101: 4494 | B101: Mccall | C101: Marisela | D101: Oklahoma | E101: (405) 555-7192 | F101: mmccall@alumni.rouxacademy.com | G101: 2.44 | H101: Graphic Design | I101: NO | K101: NO
A102: 4502 | B102: Hays | C102: Classie | D102: Nebraska | E102: (308) 555-3011 | F102: chays2@alumni.rouxacademy.com | G102: 3.5 | H102: Animation | I102: NO | K102: YES
A103: 4645 | B103: Roman | C103: Brain | D103: Texas | E103: (254) 555-2237 | F103: broman@alumni.rouxacademy.com | G103: 2.78 | H103: Graphic Design | I103: NO | K103: NO
A104: 4689 | B104: Gonzales | C104: Delinda | D104: Iowa | E104: (319) 555-7763 | F104: dgonzales2@alumni.rouxacademy.com | G104: 2.79 | H104: Fashion and Textile Design | I104: NO | K104: NO
...

Sheet Lookup Tables
C2: Lookup Tables
C6: Base Price | D6: Commission | F6: Code | G6: Tour Description | H6: Departure | I6: Base Cost | K6: Agent Name | L6: Student ID | M6: Tour Code | N6: Tour Description | O6: Departure Date | P6: Base Price of Tour
C7: 6499 | D7: 0.025 | F7: 101 | G7: Cape Town | H7: 42897 | I7: 6699 | K7: Murry | L7: 10001 | M7: 201 | N7: =VLOOKUP(M7,'Lookup Tables'!$F$7:$I$13,2) -> South Africa by Train | O7: =VLOOKUP(M7, 'Lookup Tables'!$F$7:$I$13, 3) -> 42920 | P7: =VLOOKUP(M7, 'Lookup Tables'!$F$7:$I$13, 4) -> 6999
C8: 6699 | D8: 0.03 | F8: 201 | G8: South Africa by Train | H8: 42920 | I8: 6999 | K8: Grantham | L8: 10002 | M8: 301 | N8: =VLOOKUP(M8,'Lookup Tables'!$F$7:$I$13,2) -> Kruger National Park | O8: =VLOOKUP(M8, 'Lookup Tables'!$F$7:$I$13, 3) -> 42897 | P8: =VLOOKUP(M8, 'Lookup Tables'!$F$7:$I$13, 4) -> 7199
C9: 6999 | D9: 0.035 | F9: 301 | G9: Kruger National Park | H9: 42897 | I9: 7199 | K9: Murry | L9: 10003 | M9: 101 | N9: =VLOOKUP(M9,'Lookup Tables'!$F$7:$I$13,2) -> Cape Town | O9: =VLOOKUP(M9, 'Lookup Tables'!$F$7:$I$13, 3) -> 42897 | P9: =VLOOKUP(M9, 'Lookup Tables'!$F$7:$I$13, 4) -> 6699
C10: 7199 | D10: 0.04 | F10: 401 | G10: Palace of the Lost City | H10: 42904 | I10: 8599 | K10: Fox | L10: 10004 | M10: 501 | N10: =VLOOKUP(M10,'Lookup Tables'!$F$7:$I$13,2) -> Sabi Sand Reserve | O10: =VLOOKUP(M10, 'Lookup Tables'!$F$7:$I$13, 3) -> 42911 | P10: =VLOOKUP(M10, 'Lookup Tables'!$F$7:$I$13, 4) -> 7299
C11: 7299 | D11: 0.045 | F11: 501 | G11: Sabi Sand Reserve | H11: 42911 | I11: 7299 | K11: Bingham | L11: 10005 | M11: 601 | N11: =VLOOKUP(M11,'Lookup Tables'!$F$7:$I$13,2) -> All Durban! | O11: =VLOOKUP(M11, 'Lookup Tables'!$F$7:$I$13, 3) -> 42897 | P11: =VLOOKUP(M11, 'Lookup Tables'!$F$7:$I$13, 4) -> 6499
C12: 8599 | D12: 0.05 | F12: 601 | G12: All Durban! | H12: 42897 | I12: 6499 | K12: Shannon | L12: 10006 | M12: 701 | N12: =VLOOKUP(M12,'Lookup Tables'!$F$7:$I$13,2) -> Outer Kruger Fly-in Safari | O12: =VLOOKUP(M12, 'Lookup Tables'!$F$7:$I$13, 3) -> 42911 | P12: =VLOOKUP(M12, 'Lookup Tables'!$F$7:$I$13, 4) -> 9999
C13: 9999 | D13: 0.055 | F13: 701 | G13: Outer Kruger Fly-in Safari | H13: 42911 | I13: 9999 | K13: Grantham | L13: 10007 | M13: 101 | N13: =VLOOKUP(M13,'Lookup Tables'!$F$7:$I$13,2) -> Cape Town | O13: =VLOOKUP(M13, 'Lookup Tables'!$F$7:$I$13, 3) -> 42897 | P13: =VLOOKUP(M13, 'Lookup Tables'!$F$7:$I$13, 4) -> 6699
K14: Bingham | L14: 10008 | M14: 401 | N14: =VLOOKUP(M14,'Lookup Tables'!$F$7:$I$13,2) -> Palace of the Lost City | O14: =VLOOKUP(M14, 'Lookup Tables'!$F$7:$I$13, 3) -> 42904 | P14: =VLOOKUP(M14, 'Lookup Tables'!$F$7:$I$13, 4) -> 8599
K15: Fox | L15: 10009 | M15: 501 | N15: =VLOOKUP(M15,'Lookup Tables'!$F$7:$I$13,2) -> Sabi Sand Reserve | O15: =VLOOKUP(M15, 'Lookup Tables'!$F$7:$I$13, 3) -> 42911 | P15: =VLOOKUP(M15, 'Lookup Tables'!$F$7:$I$13, 4) -> 7299
G16: Additional Information | K16: Bingham | L16: 10010 | M16: 601 | N16: =VLOOKUP(M16,'Lookup Tables'!$F$7:$I$13,2) -> All Durban! | O16: =VLOOKUP(M16, 'Lookup Tables'!$F$7:$I$13, 3) -> 42897 | P16: =VLOOKUP(M16, 'Lookup Tables'!$F$7:$I$13, 4) -> 6499
G17: Taxes and Fees | H17: 0.19 | K17: Shannon | L17: 10011 | M17: 701 | N17: =VLOOKUP(M17,'Lookup Tables'!$F$7:$I$13,2) -> Outer Kruger Fly-in Safari | O17: =VLOOKUP(M17, 'Lookup Tables'!$F$7:$I$13, 3) -> 42911 | P17: =VLOOKUP(M17, 'Lookup Tables'!$F$7:$I$13, 4) -> 9999
K18: Murry | L18: 10012 | M18: 201 | N18: =VLOOKUP(M18,'Lookup Tables'!$F$7:$I$13,2) -> South Africa by Train | O18: =VLOOKUP(M18, 'Lookup Tables'!$F$7:$I$13, 3) -> 42920 | P18: =VLOOKUP(M18, 'Lookup Tables'!$F$7:$I$13, 4) -> 6999
K19: Kinsley | L19: 10013 | M19: 401 | N19: =VLOOKUP(M19,'Lookup Tables'!$F$7:$I$13,2) -> Palace of the Lost City | O19: =VLOOKUP(M19, 'Lookup Tables'!$F$7:$I$13, 3) -> 42904 | P19: =VLOOKUP(M19, 'Lookup Tables'!$F$7:$I$13, 4) -> 8599
